<annotation>
	<folder>JPEGImages</folder>
	<filename>25.jpg</filename>
	<path>D:\VOCdevkit\VOC2007\JPEGImages\25.jpg</path>
	<source>
		<database>Unknown</database>
	</source>
	<size>
		<width>779</width>
		<height>783</height>
		<depth>3</depth>
	</size>
	<segmented>0</segmented>
	<object>
		<name>Occupancy status</name>
		<pose>Unspecified</pose>
		<truncated>1</truncated>
		<difficult>0</difficult>
		<bndbox>
			<xmin>56</xmin>
			<ymin>1</ymin>
			<xmax>286</xmax>
			<ymax>212</ymax>
		</bndbox>
	</object>
	<object>
		<name>Occupancy status</name>
		<pose>Unspecified</pose>
		<truncated>0</truncated>
		<difficult>0</difficult>
		<bndbox>
			<xmin>335</xmin>
			<ymin>22</ymin>
			<xmax>563</xmax>
			<ymax>212</ymax>
		</bndbox>
	</object>
	<object>
		<name>Occupancy status</name>
		<pose>Unspecified</pose>
		<truncated>0</truncated>
		<difficult>0</difficult>
		<bndbox>
			<xmin>434</xmin>
			<ymin>331</ymin>
			<xmax>729</xmax>
			<ymax>714</ymax>
		</bndbox>
	</object>
	<object>
		<name>Empty seat status</name>
		<pose>Unspecified</pose>
		<truncated>1</truncated>
		<difficult>0</difficult>
		<bndbox>
			<xmin>92</xmin>
			<ymin>363</ymin>
			<xmax>421</xmax>
			<ymax>783</ymax>
		</bndbox>
	</object>
</annotation>
